path_magician/__init__.py
path_magician/core_functions.py
path_magician-0.1.2.dist-info/METADATA
path_magician-0.1.2.dist-info/WHEEL
path_magician-0.1.2.dist-info/top_level.txt
path_magician-0.1.2.dist-info/RECORD
