Metadata-Version: 2.2
Name: path_magician
Version: 0.1.2
Summary: make path management easier
Author: Jiahuan
Author-email: 719481125@qq.com
Classifier: Programming Language :: Python :: 3
Classifier: License :: OSI Approved :: MIT License
Classifier: Operating System :: OS Independent
Requires-Python: >=3.8
Dynamic: author
Dynamic: author-email
Dynamic: classifier
Dynamic: requires-python
Dynamic: summary
